frbb.py
frbb-1.0.0.dist-info/METADATA
frbb-1.0.0.dist-info/WHEEL
frbb-1.0.0.dist-info/top_level.txt
frbb-1.0.0.dist-info/RECORD
